xterm-util-Marcelo-Perseus/__init__.py
xterm-util-Marcelo-Perseus/xtermutil.py
xtermutil/__init__.py
xtermutil/xtermutil.py
xtermutil-0.0.3.dist-info/LICENSE
xtermutil-0.0.3.dist-info/METADATA
xtermutil-0.0.3.dist-info/WHEEL
xtermutil-0.0.3.dist-info/top_level.txt
xtermutil-0.0.3.dist-info/RECORD
