Metadata-Version: 2.1
Name: xtermutil
Version: 0.0.3
Summary: A package to help customize xterm
Home-page: https://github.com/Marcelo-Perseus/xterm-util
Author: Marcelo Luciano
Author-email: Marcelo.Perseus@gmail.com
License: UNKNOWN
Project-URL: Bug Tracker, https://github.com/Marcelo-Perseus/xterm-util/issues
Platform: UNKNOWN
Classifier: Programming Language :: Python :: 3
Classifier: License :: OSI Approved :: MIT License
Classifier: Operating System :: POSIX :: Linux
Requires-Python: >=3.6
